build/lib/build/lib/docs/conf.py
build/lib/build/lib/examples/emnist_fed_avg.py
build/lib/build/lib/examples/fed_avg.py
build/lib/build/lib/examples/fed_avg_test.py
build/lib/build/lib/examples/stateful_fed_avg.py
build/lib/build/lib/examples/stateful_fed_avg_test.py
build/lib/build/lib/experiments/fed_avg/run_fed_avg.py
build/lib/build/lib/fedjax/__init__.py
build/lib/build/lib/fedjax/fedjax_test.py
build/lib/build/lib/fedjax/version.py
build/lib/build/lib/fedjax/aggregators/__init__.py
build/lib/build/lib/fedjax/aggregators/aggregator.py
build/lib/build/lib/fedjax/aggregators/aggregator_test.py
build/lib/build/lib/fedjax/aggregators/compression.py
build/lib/build/lib/fedjax/aggregators/compression_test.py
build/lib/build/lib/fedjax/aggregators/walsh_hadamard.py
build/lib/build/lib/fedjax/aggregators/walsh_hadamard_test.py
build/lib/build/lib/fedjax/algorithms/__init__.py
build/lib/build/lib/fedjax/algorithms/agnostic_fed_avg.py
build/lib/build/lib/fedjax/algorithms/agnostic_fed_avg_test.py
build/lib/build/lib/fedjax/algorithms/apfl.py
build/lib/build/lib/fedjax/algorithms/apfl_test.py
build/lib/build/lib/fedjax/algorithms/fed_avg.py
build/lib/build/lib/fedjax/algorithms/fed_avg_test.py
build/lib/build/lib/fedjax/algorithms/fed_prox.py
build/lib/build/lib/fedjax/algorithms/fed_prox_test.py
build/lib/build/lib/fedjax/algorithms/hyp_cluster.py
build/lib/build/lib/fedjax/algorithms/hyp_cluster_test.py
build/lib/build/lib/fedjax/algorithms/mime.py
build/lib/build/lib/fedjax/algorithms/mime_lite.py
build/lib/build/lib/fedjax/algorithms/mime_lite_test.py
build/lib/build/lib/fedjax/algorithms/mime_test.py
build/lib/build/lib/fedjax/core/__init__.py
build/lib/build/lib/fedjax/core/client_datasets.py
build/lib/build/lib/fedjax/core/client_datasets_benchmark.py
build/lib/build/lib/fedjax/core/client_datasets_test.py
build/lib/build/lib/fedjax/core/client_samplers.py
build/lib/build/lib/fedjax/core/client_samplers_test.py
build/lib/build/lib/fedjax/core/dataclasses.py
fedjax-0.0.17.dist-info/LICENSE
fedjax-0.0.17.dist-info/METADATA
fedjax-0.0.17.dist-info/WHEEL
fedjax-0.0.17.dist-info/top_level.txt
fedjax-0.0.17.dist-info/RECORD
