Metadata-Version: 2.1
Name: fedjax
Version: 0.0.17
Summary: Federated learning simulation with JAX.
Home-page: https://github.com/google/fedjax
Author: FedJAX Team
Author-email: no-reply@google.com
License: Apache 2.0
Keywords: federated python machine learning
Classifier: Development Status :: 3 - Alpha
Classifier: Intended Audience :: Developers
Classifier: Intended Audience :: Science/Research
Classifier: License :: OSI Approved :: Apache Software License
Classifier: Programming Language :: Python :: 3.8
Classifier: Programming Language :: Python :: 3.9
Classifier: Programming Language :: Python :: 3.10
Classifier: Topic :: Scientific/Engineering :: Artificial Intelligence
Requires-Python: >=3.8
License-File: LICENSE
Requires-Dist: absl-py
Requires-Dist: dm-haiku
Requires-Dist: jax (>=0.4.4)
Requires-Dist: jaxlib
Requires-Dist: msgpack
Requires-Dist: optax
Requires-Dist: requests
Requires-Dist: scipy
